covid19openapi/__init__.py
covid19openapi/basecovid19.py
covid19openapi/config.py
covid19openapi/covid19scope.py
covid19openapi/thaicovid19.py
covid19_open_api-0.0.2.dist-info/LICENSE.md
covid19_open_api-0.0.2.dist-info/METADATA
covid19_open_api-0.0.2.dist-info/WHEEL
covid19_open_api-0.0.2.dist-info/top_level.txt
covid19_open_api-0.0.2.dist-info/RECORD
