Metadata-Version: 2.1
Name: covid19-open-api
Version: 0.0.2
Summary: Thai Covid-19 status
Home-page: https://github.com/rsxss/covid19-open-api
Author: Natworpong Loyswai
Author-email: Natworpong.Loyswai@mail.kmutt.ac.th
License: UNKNOWN
Keywords: covid19
Platform: UNKNOWN
Classifier: Programming Language :: Python :: 3
Requires-Dist: requests (==2.23.0)
